texnomagic/__init__.py
texnomagic/abc.py
texnomagic/abcs.py
texnomagic/cli.py
texnomagic/cli_common.py
texnomagic/client.py
texnomagic/common.py
texnomagic/console.py
texnomagic/drawing.py
texnomagic/ex.py
texnomagic/jsonrpcserver.py
texnomagic/lang.py
texnomagic/model.py
texnomagic/mods.py
texnomagic/render.py
texnomagic/requests.py
texnomagic/server.py
texnomagic/symbol.py
texnomagic/commands/__init__.py
texnomagic/commands/abc.py
texnomagic/commands/drawing.py
texnomagic/commands/mod.py
texnomagic/commands/paths.py
texnomagic/commands/server.py
texnomagic/commands/spell.py
texnomagic/commands/symbol.py
texnomagic-0.8.0.dist-info/METADATA
texnomagic-0.8.0.dist-info/WHEEL
texnomagic-0.8.0.dist-info/entry_points.txt
texnomagic-0.8.0.dist-info/licenses/LICENSE
texnomagic-0.8.0.dist-info/RECORD
