Metadata-Version: 2.3
Name: texnomagic
Version: 0.8.0
Summary: TexnoMagic module for digital Magic
Project-URL: Bug Tracker, https://github.com/texnoforge/texnomagic/issues
Project-URL: Docs, https://texnoforge.github.io/texnomagic
Project-URL: Homepage, https://github.com/texnoforge/texnomagic/
Author-email: texnoforge <voice@texnoforge.dev>
License-Expression: MIT
License-File: LICENSE
Classifier: License :: OSI Approved :: MIT License
Classifier: Operating System :: OS Independent
Classifier: Programming Language :: Python :: 3
Requires-Dist: click
Requires-Dist: parsimonious
Requires-Dist: pyyaml
Requires-Dist: requests
Requires-Dist: rich
Requires-Dist: scikit-learn
Requires-Dist: toml
Provides-Extra: jsonrpc
Requires-Dist: jsonrpcserver>=5; extra == 'jsonrpc'
Provides-Extra: png
Requires-Dist: pillow; extra == 'png'
